listaprimo/__init__.py
listaprimo-1.0.dist-info/LICENSE.txt
listaprimo-1.0.dist-info/METADATA
listaprimo-1.0.dist-info/WHEEL
listaprimo-1.0.dist-info/top_level.txt
listaprimo-1.0.dist-info/RECORD
