Metadata-Version: 2.1
Name: listaprimo
Version: 1.0
Summary: A tool to list prime numbers between 1 and n.
Home-page: UNKNOWN
Author: David Jerez
Author-email: davjersor@gmail.com
License: GNU GPLv3
Keywords: listaprimo primos mathematical
Platform: UNKNOWN
Classifier: Development Status :: 4 - Beta
Classifier: Intended Audience :: Developers
Classifier: Topic :: Utilities
Classifier: License :: OSI Approved :: GNU General Public License v3 (GPLv3)
Classifier: Programming Language :: Python :: 3
Classifier: Operating System :: OS Independent
